{"name":"LeetCode","slug":"LeetCode","count":10,"postlist":[{"title":"LeetCode-每日一题堆复习-C++","uid":"45dcfdf945d10b0febeb53e963670eb2","slug":"LeetCode每日一题-堆","date":"2023-12-23T01:52:13.000Z","updated":"2023-12-24T08:08:28.853Z","comments":true,"path":"api/articles/LeetCode每日一题-堆.json","keywords":null,"cover":"https://cdn.jsdelivr.net/gh/cyl-ly/picture/blogimage/202312231105816.png","text":"每日一题堆复习...","permalink":"/post/LeetCode每日一题-堆","photos":[],"count_time":{"symbolsCount":"3.9k","symbolsTime":"4 mins."},"categories":[{"name":"LeetCode","slug":"LeetCode","count":10,"path":"api/categories/LeetCode.json"}],"tags":[{"name":"LeetCode","slug":"LeetCode","count":10,"path":"api/tags/LeetCode.json"}],"author":{"name":"CYLIN","slug":"blog-author","avatar":"https://cdn.jsdelivr.net/gh/cyl-ly/picture/blogimage/202312241427715.jpg","link":"/","description":"多读书多看报，少吃零食多睡觉","socials":{"github":"","twitter":"","stackoverflow":"","wechat":"","qq":"","weibo":"","zhihu":"","csdn":"","juejin":"","customs":{}}}},{"title":"LeetCode-每日一题二分法，理解再次深刻-C++","uid":"13311aa294e657eaef79fbe3e5c5f789","slug":"LeetCode二分法","date":"2023-12-18T02:30:07.000Z","updated":"2023-12-19T01:27:18.082Z","comments":true,"path":"api/articles/LeetCode二分法.json","keywords":null,"cover":[],"text":"LeetCode-每日一题二分法，理解再次深刻-C++162.寻找峰值 峰值元素是指其值严格大于左右相邻值的元素。 给你一个整数数组 nums，找到峰值元素并返...","permalink":"/post/LeetCode二分法","photos":[],"count_time":{"symbolsCount":"4k","symbolsTime":"4 mins."},"categories":[{"name":"LeetCode","slug":"LeetCode","count":10,"path":"api/categories/LeetCode.json"}],"tags":[{"name":"LeetCode","slug":"LeetCode","count":10,"path":"api/tags/LeetCode.json"}],"author":{"name":"CYLIN","slug":"blog-author","avatar":"https://cdn.jsdelivr.net/gh/cyl-ly/picture/blogimage/202312241427715.jpg","link":"/","description":"多读书多看报，少吃零食多睡觉","socials":{"github":"","twitter":"","stackoverflow":"","wechat":"","qq":"","weibo":"","zhihu":"","csdn":"","juejin":"","customs":{}}}},{"title":"记LeetCode每日一题二维前缀和+复习-C++","uid":"eae7f0e66f161da71809800607dd862f","slug":"力扣二维前缀和","date":"2023-12-14T01:27:36.000Z","updated":"2023-12-14T01:35:20.534Z","comments":true,"path":"api/articles/力扣二维前缀和.json","keywords":null,"cover":[],"text":"2132.用邮票贴满网格图 给你一个 m x n 的二进制矩阵 grid ，每个格子要么为 0 （空）要么为 1 （被占据）。 给你邮票的尺寸为 stampHe...","permalink":"/post/力扣二维前缀和","photos":[],"count_time":{"symbolsCount":"2.3k","symbolsTime":"2 mins."},"categories":[{"name":"LeetCode","slug":"LeetCode","count":10,"path":"api/categories/LeetCode.json"}],"tags":[{"name":"LeetCode","slug":"LeetCode","count":10,"path":"api/tags/LeetCode.json"}],"author":{"name":"CYLIN","slug":"blog-author","avatar":"https://cdn.jsdelivr.net/gh/cyl-ly/picture/blogimage/202312241427715.jpg","link":"/","description":"多读书多看报，少吃零食多睡觉","socials":{"github":"","twitter":"","stackoverflow":"","wechat":"","qq":"","weibo":"","zhihu":"","csdn":"","juejin":"","customs":{}}}},{"title":"记LeetCode每日一题-单调栈Plus+复习单调栈-C++","uid":"16628ff8472695adf497f3bbda476921","slug":"力扣每日一次-单调栈Plus","date":"2023-12-12T03:30:20.000Z","updated":"2023-12-21T02:27:01.964Z","comments":true,"path":"api/articles/力扣每日一次-单调栈Plus.json","keywords":null,"cover":[],"text":"单调栈 求下个更大的元素 &#x2F; 下下个 求单调的前缀和、后缀和 2454.下一个更大的元素IV 给你一个下标从 0 开始的非负整数数组 nums 。对于...","permalink":"/post/力扣每日一次-单调栈Plus","photos":[],"count_time":{"symbolsCount":"5.2k","symbolsTime":"5 mins."},"categories":[{"name":"LeetCode","slug":"LeetCode","count":10,"path":"api/categories/LeetCode.json"}],"tags":[{"name":"LeetCode","slug":"LeetCode","count":10,"path":"api/tags/LeetCode.json"}],"author":{"name":"CYLIN","slug":"blog-author","avatar":"https://cdn.jsdelivr.net/gh/cyl-ly/picture/blogimage/202312241427715.jpg","link":"/","description":"多读书多看报，少吃零食多睡觉","socials":{"github":"","twitter":"","stackoverflow":"","wechat":"","qq":"","weibo":"","zhihu":"","csdn":"","juejin":"","customs":{}}}},{"title":"记LeetCode每日一题的BFS-C++","uid":"5f95f7d2ef3a6fe783c81502ace87b9b","slug":"BFS","date":"2023-12-12T01:37:24.000Z","updated":"2023-12-12T05:06:39.142Z","comments":true,"path":"api/articles/BFS.json","keywords":null,"cover":[],"text":"1631.最小体力消耗路径 你准备参加一场远足活动。给你一个二维 rows x columns 的地图 heights ，其中 heights[row][col...","permalink":"/post/BFS","photos":[],"count_time":{"symbolsCount":"7.1k","symbolsTime":"6 mins."},"categories":[{"name":"LeetCode","slug":"LeetCode","count":10,"path":"api/categories/LeetCode.json"}],"tags":[{"name":"LeetCode","slug":"LeetCode","count":10,"path":"api/tags/LeetCode.json"}],"author":{"name":"CYLIN","slug":"blog-author","avatar":"https://cdn.jsdelivr.net/gh/cyl-ly/picture/blogimage/202312241427715.jpg","link":"/","description":"多读书多看报，少吃零食多睡觉","socials":{"github":"","twitter":"","stackoverflow":"","wechat":"","qq":"","weibo":"","zhihu":"","csdn":"","juejin":"","customs":{}}}},{"title":"《力扣面试150题》题单拓展——位运算","uid":"61e7d4341862c95b647f5296813cf0dc","slug":"力扣位运算","date":"2023-12-10T12:03:57.000Z","updated":"2023-12-10T12:18:33.422Z","comments":true,"path":"api/articles/力扣位运算.json","keywords":null,"cover":null,"text":"《力扣面试150题》题单拓展——位运算1.基础知识 运算 符号 解读 并集 | ans &#x3D; ans |4;(1000 ∪ 0010) &#x3D; 1...","permalink":"/post/力扣位运算","photos":[],"count_time":{"symbolsCount":680,"symbolsTime":"1 mins."},"categories":[{"name":"LeetCode","slug":"LeetCode","count":10,"path":"api/categories/LeetCode.json"}],"tags":[{"name":"LeetCode","slug":"LeetCode","count":10,"path":"api/tags/LeetCode.json"}],"author":{"name":"CYLIN","slug":"blog-author","avatar":"https://cdn.jsdelivr.net/gh/cyl-ly/picture/blogimage/202312241427715.jpg","link":"/","description":"多读书多看报，少吃零食多睡觉","socials":{"github":"","twitter":"","stackoverflow":"","wechat":"","qq":"","weibo":"","zhihu":"","csdn":"","juejin":"","customs":{}}}},{"title":"《力扣面试150题》题单拓展——双指针","uid":"5b133869c321e07b89f988d13857b0f6","slug":"力扣双指针","date":"2023-12-10T12:03:51.000Z","updated":"2023-12-10T12:20:31.637Z","comments":true,"path":"api/articles/力扣双指针.json","keywords":null,"cover":[],"text":"《力扣面试150题》题单拓展——双指针1.基础知识 为什么双指针会正确？不会漏掉搜索空间 数组nums递增排序，假设共8个元素 假设由于搜索空间i &lt; j...","permalink":"/post/力扣双指针","photos":[],"count_time":{"symbolsCount":"1.1k","symbolsTime":"1 mins."},"categories":[{"name":"LeetCode","slug":"LeetCode","count":10,"path":"api/categories/LeetCode.json"}],"tags":[{"name":"LeetCode","slug":"LeetCode","count":10,"path":"api/tags/LeetCode.json"}],"author":{"name":"CYLIN","slug":"blog-author","avatar":"https://cdn.jsdelivr.net/gh/cyl-ly/picture/blogimage/202312241427715.jpg","link":"/","description":"多读书多看报，少吃零食多睡觉","socials":{"github":"","twitter":"","stackoverflow":"","wechat":"","qq":"","weibo":"","zhihu":"","csdn":"","juejin":"","customs":{}}}},{"title":"《力扣面试150题》题单拓展——回溯","uid":"a9b8b88776cf51b021505ec6036cee86","slug":"力扣回溯","date":"2023-12-10T12:03:44.000Z","updated":"2023-12-10T12:18:33.429Z","comments":true,"path":"api/articles/力扣回溯.json","keywords":null,"cover":null,"text":"《力扣面试150题》题单拓展——回溯1.基础知识1234567891011121314void find(string &amp;s, int i, strin...","permalink":"/post/力扣回溯","photos":[],"count_time":{"symbolsCount":"2.5k","symbolsTime":"2 mins."},"categories":[{"name":"LeetCode","slug":"LeetCode","count":10,"path":"api/categories/LeetCode.json"}],"tags":[{"name":"LeetCode","slug":"LeetCode","count":10,"path":"api/tags/LeetCode.json"}],"author":{"name":"CYLIN","slug":"blog-author","avatar":"https://cdn.jsdelivr.net/gh/cyl-ly/picture/blogimage/202312241427715.jpg","link":"/","description":"多读书多看报，少吃零食多睡觉","socials":{"github":"","twitter":"","stackoverflow":"","wechat":"","qq":"","weibo":"","zhihu":"","csdn":"","juejin":"","customs":{}}}},{"title":"《力扣面试150题》题单拓展——滑动窗口","uid":"653a563cd8843e1e667b0cd176929948","slug":"力扣滑动窗口","date":"2023-12-10T12:03:36.000Z","updated":"2023-12-10T12:18:33.432Z","comments":true,"path":"api/articles/力扣滑动窗口.json","keywords":null,"cover":null,"text":"《力扣面试150题》题单拓展——滑动窗口1.基础知识 先区分好，枚举右端点，还是左端点， 窗口内的条件改变后，一般都是while控制另一个窗口的移动，然后收集结...","permalink":"/post/力扣滑动窗口","photos":[],"count_time":{"symbolsCount":"1.2k","symbolsTime":"1 mins."},"categories":[{"name":"LeetCode","slug":"LeetCode","count":10,"path":"api/categories/LeetCode.json"}],"tags":[{"name":"LeetCode","slug":"LeetCode","count":10,"path":"api/tags/LeetCode.json"}],"author":{"name":"CYLIN","slug":"blog-author","avatar":"https://cdn.jsdelivr.net/gh/cyl-ly/picture/blogimage/202312241427715.jpg","link":"/","description":"多读书多看报，少吃零食多睡觉","socials":{"github":"","twitter":"","stackoverflow":"","wechat":"","qq":"","weibo":"","zhihu":"","csdn":"","juejin":"","customs":{}}}},{"title":"《力扣面试150题》题单拓展——二分法","uid":"862c53dc23880fc1e11ce2e51710e434","slug":"力扣二分法","date":"2023-12-10T12:03:09.000Z","updated":"2023-12-10T12:15:11.766Z","comments":true,"path":"api/articles/力扣二分法.json","keywords":null,"cover":null,"text":"《力扣面试150题》题单拓展——二分法 困难题：找第K大&#x2F;小 最大化最小值 1. 基础知识 首先可以确定答案的上下界 单调性分析：如果当前答案为m时，...","permalink":"/post/力扣二分法","photos":[],"count_time":{"symbolsCount":"1.3k","symbolsTime":"1 mins."},"categories":[{"name":"LeetCode","slug":"LeetCode","count":10,"path":"api/categories/LeetCode.json"}],"tags":[{"name":"LeetCode","slug":"LeetCode","count":10,"path":"api/tags/LeetCode.json"}],"author":{"name":"CYLIN","slug":"blog-author","avatar":"https://cdn.jsdelivr.net/gh/cyl-ly/picture/blogimage/202312241427715.jpg","link":"/","description":"多读书多看报，少吃零食多睡觉","socials":{"github":"","twitter":"","stackoverflow":"","wechat":"","qq":"","weibo":"","zhihu":"","csdn":"","juejin":"","customs":{}}}}]}